client_side/__init__.py
client_side/apps.py
client_side/component.py
client_side/templates/client_side/link.html
client_side/templates/client_side/script.html
client_side/templatetags/__init__.py
client_side/templatetags/dependency_tags.py
django_client_side-0.3.1.dist-info/LICENSE
django_client_side-0.3.1.dist-info/METADATA
django_client_side-0.3.1.dist-info/WHEEL
django_client_side-0.3.1.dist-info/entry_points.txt
django_client_side-0.3.1.dist-info/top_level.txt
django_client_side-0.3.1.dist-info/RECORD
