Metadata-Version: 2.1
Name: django-client-side
Version: 0.3.1
Summary: Simple client-side dependency management for your django project.
Author-email: powderflask <powderflask@gmail.com>
License: MIT License
Project-URL: Homepage, https://github.com/powderflask/django-client-side
Project-URL: Repository, https://github.com/powderflask/django-client-side
Keywords: django-client-side
Classifier: Development Status :: 4 - Beta
Classifier: License :: OSI Approved :: MIT License
Classifier: Intended Audience :: Developers
Classifier: Natural Language :: English
Classifier: Programming Language :: Python :: 3
Classifier: Framework :: Django
Requires-Python: <4.0,>=3.8
License-File: LICENSE
Requires-Dist: django
Provides-Extra: style
Requires-Dist: black ; extra == 'style'
Requires-Dist: isort ; extra == 'style'
Requires-Dist: flake8 ; extra == 'style'
Requires-Dist: flake8-bugbear ; extra == 'style'
Provides-Extra: test
Requires-Dist: tox ; extra == 'test'
Requires-Dist: pytest ; extra == 'test'
Requires-Dist: pytest-django ; extra == 'test'
Requires-Dist: pytest-cov ; extra == 'test'
Requires-Dist: pytest-sugar ; extra == 'test'
Provides-Extra: utils
Requires-Dist: invoke ; extra == 'utils'
Requires-Dist: bumpver ; extra == 'utils'
Requires-Dist: build ; extra == 'utils'
Requires-Dist: twine ; extra == 'utils'
Requires-Dist: pip-tools ; extra == 'utils'
